Metadata-Version: 1.2
Name: ceribou
Version: 0.0.4
Summary: ceribou is a python package for delicious ceribou recipes.
Home-page: https://github.com/Bosmansc/Caribouce
Author: Cederic Bosmans
Author-email: mail@gmail.com
License: MIT
Platform: UNKNOWN
Classifier: Development Status :: 4 - Beta
Classifier: License :: OSI Approved :: MIT License
Classifier: Programming Language :: Python
Classifier: Programming Language :: Python :: 3.5
Classifier: Programming Language :: Python :: 3.6
Classifier: Topic :: Software Development :: Libraries
Classifier: Topic :: Software Development :: Libraries :: Python Modules
Classifier: Intended Audience :: Developers
Requires-Python: >=3.5
